LICENSE
MANIFEST.in
README.rst
setup.py
CreateManifest.egg-info/PKG-INFO
CreateManifest.egg-info/SOURCES.txt
CreateManifest.egg-info/dependency_links.txt
CreateManifest.egg-info/top_level.txt
src/__init__.py
src/core.py
src/helpers/__init__.py
src/helpers/xml_helpers.py