Metadata-Version: 2.1
Name: CreateManifest
Version: 0.1.0
Summary: Package to create manifest file
Home-page: UNKNOWN
Author: Nitesh Agarwal
Author-email: nitesh.agarwal@gmail.com
License: Copyright (c) 2021, Nitesh Agarwal
Platform: UNKNOWN
License-File: LICENSE
